[["achievements",{"version":2,"data":{"vecHighlight":[],"vecUnachieved":[],"vecAchievedHidden":[],"nTotal":0,"nAchieved":0}}],["socialmedia",{"version":3,"data":[]}],["associations",{"version":2,"data":{"rgDevelopers":[{"strName":"Get(Color) Games","strURL":null}],"rgPublishers":[{"strName":"Get(Color) Games","strURL":null}],"rgFranchises":[]}}],["descriptions",{"version":1,"data":{"strFullDescription":"Download the Wormtown Friend's Pass and play Last Train Outta' Wormtown with your friends for free!\r\n\r\nThis version of Wormtown allows joining private games hosted by players who own the full copy of Wormtown.\r\n\r\nHow it works:\r\n[list][*]Simply download the Wormtown Friend's Pass\r\n[*]Join your friend using their lobby code\r\n[*]Have fun![/list]\r\n\r\nIf you enjoy the game, consider picking up your own copy to unlock the full features of the game, like:\r\n- Additional cosmetic and player customization options\r\n- Hosting your own games or joining public Quickplay lobbies\r\n- Player progression and Steam Achievements (Coming Soon!)","strSnippet":"Download the Wormtown Friend's Pass and play Last Train Outta' Wormtown with your friends for free!"}}],["achievementmap",{"version":5,"data":"[]"}],["usernews",{"version":5,"data":["CB4Q9NDGsAYZhyuIBAEAEAEhAAAAAAAAAAApoB0kAAAAAAA=","CB4Qns/GsAYZb3tTDAEAEAEhAAAAAAAAAAApoB0kAAAAAAA=","CB4Q84W+sAYZS0gmCAEAEAEhAAAAAAAAAAApoB0kAAAAAAA=","CB4Q4vC9sAYZC71pBQEAEAEhAAAAAAAAAAApoB0kAAAAAAA=","CB4Q4OLGsAYZr5KuCAEAEAEhAAAAAAAAAAApoB0kAAAAAAA="]}],["gameactivity",{"version":5,"data":[]}]]